notetools/__init__.py
notetools/colab/__init__.py
notetools/colab/constants.py
notetools/colab/views.py
notetools-0.0.1.dist-info/LICENSE
notetools-0.0.1.dist-info/METADATA
notetools-0.0.1.dist-info/WHEEL
notetools-0.0.1.dist-info/top_level.txt
notetools-0.0.1.dist-info/RECORD
